.pylintrc
README
build.vel
setup.py
docs/api/api-objects.txt
docs/api/class-tree.html
docs/api/crarr.png
docs/api/epydoc.css
docs/api/epydoc.js
docs/api/frames.html
docs/api/help.html
docs/api/identifier-index.html
docs/api/index.html
docs/api/module-tree.html
docs/api/redirect.html
docs/api/toc-everything.html
docs/api/toc-webf-module.html
docs/api/toc-webf.cli-module.html
docs/api/toc-webf.webflib-module.html
docs/api/toc.html
docs/api/webf-module.html
docs/api/webf-pysrc.html
docs/api/webf.cli-module.html
docs/api/webf.cli-pysrc.html
docs/api/webf.cli.WebFaction-class.html
docs/api/webf.webflib-module.html
docs/api/webf.webflib-pysrc.html
docs/api/webf.webflib.WebFactionXmlRpc-class.html
webf/__init__.py
webf/cli.py
webf/webflib.py
webf.egg-info/PKG-INFO
webf.egg-info/SOURCES.txt
webf.egg-info/dependency_links.txt
webf.egg-info/entry_points.txt
webf.egg-info/requires.txt
webf.egg-info/top_level.txt