Metadata-Version: 1.0
Name: webf
Version: 0.1.0
Summary: Command-line tool and library for the WebFaction API.
Home-page: http://trac.doapspace.org/webf
Author: Rob Cakebread
Author-email: <rob@cakebread.info>
License: BSD-2
Keywords: webf webfaction xmlrpc
Platform: UNKNOWN
Classifier: Development Status :: 2 - Pre-Alpha
Classifier: Intended Audience :: Developers
Classifier: Intended Audience :: End Users/Desktop
Classifier: License :: OSI Approved :: BSD License
Classifier: Programming Language :: Python
Classifier: Topic :: Software Development :: Libraries :: Python Modules
